{
    "datasetName": "uwvehicles",
    "enable": true,
    "datasetTypeName": "database",
    "databaseName": "GIGINSDATA",
    "datasetSchema": "dbo",
    "skipProductLoad": false,
    "sourceSystemProperties": {
        "sourceSystemName": "IIS",
        "includeSpecificColumns": [
            "vehicleid",
            "transaction_source_id",
            "renewal_source_id",
            "qsid_vehicle",
            "qsid",
            "vehiclenum",
            "locnum",
            "code",
            "vin",
            "vinvalidated",
            "modelyear",
            "make",
            "model",
            "msrp",
            "vehicletype",
            "vehiclesize",
            "businessuseclass",
            "radiusofoperation",
            "secondaryclass",
            "secondaryclasstype",
            "usedindumping",
            "xtype",
            "operator",
            "operatoruse",
            "trailertype",
            "registeredto",
            "seatingcapacity",
            "employervanpool",
            "safetyfeatures",
            "ar_category1",
            "ar_category2",
            "ar_category3",
            "ar_category4",
            "startdate",
            "enddate",
            "deletedon",
            "readyforrating",
            "enteredon",
            "enteredby",
            "updateon",
            "updateby",
            "isfleet",
            "classcode",
            "territory",
            "revision",
            "admodcost",
            "performcontractedwork",
            "deliveries",
            "dropofflocation",
            "uwvehiclestrimid",
            "auxrunninglamps",
            "antitheftdevices",
            "applyaccprevcredit",
            "trailertovehicleid",
            "enteredweight",
            "antitheftdiscount",
            "mechlift",
            "registeredtoname",
            "registeredtostate",
            "isinterstatetravel",
            "ispublicdelivery",
            "truckbodyvalue",
            "truckbodydescription",
            "truckbodysubtype",
            "truckbodytype",
            "completeincomplete",
            "averageannualmileage",
            "yearsowned",
            "nonsevereaccidents"
        ],
        "ingestType": "watermark",
        "sourceWatermarkIdentifier": "isnull(updateon, enteredon)",
        "isDynamicQuery": true
    },
    "rawProperties": {
        "lakehouseName": "den_lhw_dpr_001_raw_files",
        "fileType": "parquet",
        "directoryName": "IIS_GIGINSDATA"
    },
    "curatedProperties": {
        "lakehouseName": "den_lhw_scu_001_policy_curated",
        "schemaName": "cauto",
        "fileOptions": {
            "encoding": "ISO-8859-1",
            "header": true,
            "inferColumnTypes": true,
            "multiline": true,
            "delimiter": ",",
            "escape": "\"",
            "timestampFormat": "dd/MM/yyyy"
        },
        "columnList": [
            "*"
        ],
        "primaryKeyList": [
            "vehicleID",
            "transaction_source_id",
            "vehicleNum",
            "locnum",
            "code",
            "vin",
            "ModelYear",
            "Make",
            "Model",
            "VehicleType",
            "startDate",
            "endDate",
            "deletedOn",
            "classCode",
            "Revision"
        ],
        "duplicateCheckEnabled": false,
        "targetFileFormat": "delta",
        "targetLoadType": "merge"
    }
}